<?xml version="1.0" encoding="UTF-8"?>
<beans xmlns="http://www.springframework.org/schema/beans" xmlns:xsi="http://www.w3.org/2001/XMLSchema-instance"
	xsi:schemaLocation="http://www.springframework.org/schema/beans http://www.springframework.org/schema/beans/spring-beans-4.0.xsd">

	<bean name="propertiesService" class="egovframework.rte.fdl.property.impl.EgovPropertyServiceImpl" destroy-method="destroy">
		<property name="properties">
	        <map>
	        	<entry key="pageUnit" value="15"/>
	        	<entry key="pageSize" value="10"/>
	        	<entry key="posblAtchFileSize" value="5242880"/>
	        	
	        	<entry key="Globals.fileStorePath" value="webapps/sbfile/"/>
	        	<entry key="Globals.addedOptions" value="false"/>
	        	
	        	<entry key="Globals.nc.user" value="stderp" />
	        	<entry key="Globals.nc.rootFolder" value="ERP" />
	        	
	        	<!-- 41번서버 -->
<!-- 	        	
	        	<entry key="Globals.nc.webdav.base" value="http://172.22.0.41:8090/remote.php/dav/files" />
	        	<entry key="Globals.nc.appPassword" value="WmwHN-XiqtG-5WWk6-J6HAJ-Awji8" />
	        	<entry key="Globals.nc.base" value="http://172.22.0.41:8090" />
	        	<entry key="Globals.nc.shareToken" value="CC2GXsoEBqsN859" />
 -->       	
	        	<!-- 테스트서버 -->
	        	<entry key="Globals.nc.webdav.base" value="http://172.22.1.138:8090/remote.php/dav/files" />
	        	<entry key="Globals.nc.appPassword" value="9iCt3-6qNnH-LQGWY-wr79J-H2dxD" />
	        	<entry key="Globals.nc.base" value="http://172.22.1.138:8090" />
	        	<entry key="Globals.nc.shareToken" value="sBCKWAALbGdGw7g" />

	        	<entry key="img.url" value="/api/file/getImage.do?atchFileId=" />
	        	
	        	
	        </map>
		</property>
	</bean>
	
</beans>	
